README.rst
setup.py
pyramid_translogger/__init__.py
pyramid_translogger/compat.py
pyramid_translogger.egg-info/PKG-INFO
pyramid_translogger.egg-info/SOURCES.txt
pyramid_translogger.egg-info/dependency_links.txt
pyramid_translogger.egg-info/entry_points.txt
pyramid_translogger.egg-info/not-zip-safe
pyramid_translogger.egg-info/requires.txt
pyramid_translogger.egg-info/top_level.txt
pyramid_translogger/tests/__init__.py