Metadata-Version: 1.1
Name: pyramid-translogger
Version: 0.1
Summary: access log logger tween (almost stolen from Paste.translogger)
Home-page: https://github.com/podhmo/pyramid_translogger
Author: UNKNOWN
Author-email: UNKNOWN
License: UNKNOWN
Platform: UNKNOWN
Classifier: Programming Language :: Python
Classifier: Programming Language :: Python :: Implementation :: CPython
